feagi_connector_gazebo/__init__.py
feagi_connector_gazebo/parser/__init__.py
feagi_connector_gazebo/parser/config_parser.py
feagi_connector_gazebo/parser/feagi_config_template.json
feagi_connector_gazebo/parser/gazebo_config_template.json
feagi_connector_gazebo-0.0.4.dist-info/licenses/LICENSE
feagi_connector_gazebo-0.0.4.dist-info/METADATA
feagi_connector_gazebo-0.0.4.dist-info/WHEEL
feagi_connector_gazebo-0.0.4.dist-info/top_level.txt
feagi_connector_gazebo-0.0.4.dist-info/RECORD
